mpl2tex/__init__.py
mpl2tex/figtotex.py
mpl2tex/texfig.py
mpl2tex/template/__init__.py
mpl2tex/template/template.tex
mpl2tex-0.0.1.dist-info/licenses/LICENSE
mpl2tex-0.0.1.dist-info/METADATA
mpl2tex-0.0.1.dist-info/WHEEL
mpl2tex-0.0.1.dist-info/top_level.txt
mpl2tex-0.0.1.dist-info/RECORD
