Metadata-Version: 2.4
Name: mpl2tex
Version: 0.0.1
Summary: Package to output matplotlib figures to latex.
Author-email: Ethan C Strayer <ethancstrayer@gmail.com>
License-Expression: MPL-2.0
Project-URL: homepage, https://github.com/ecstrayer/mpl2tex
Requires-Python: >=3.9
License-File: LICENSE
Requires-Dist: matplotlib
Dynamic: license-file
